pybit/__init__.py
pybit/_helpers.py
pybit/_http_manager.py
pybit/_v5_account.py
pybit/_v5_asset.py
pybit/_v5_broker.py
pybit/_v5_market.py
pybit/_v5_misc.py
pybit/_v5_position.py
pybit/_v5_pre_upgrade.py
pybit/_v5_spot_leverage_token.py
pybit/_v5_spot_margin_trade.py
pybit/_v5_trade.py
pybit/_v5_user.py
pybit/_websocket_stream.py
pybit/account.py
pybit/asset.py
pybit/broker.py
pybit/exceptions.py
pybit/helpers.py
pybit/market.py
pybit/misc.py
pybit/position.py
pybit/pre_upgrade.py
pybit/spot_leverage_token.py
pybit/spot_margin_trade.py
pybit/trade.py
pybit/unified_trading.py
pybit/user.py
pybit/legacy/__init__.py
pybit/legacy/_helpers.py
pybit/legacy/_http_manager.py
pybit/legacy/_websocket_stream.py
pybit/legacy/copy_trading.py
pybit/legacy/exceptions.py
pybit/legacy/usdc_options.py
pybit/legacy/usdc_perpetual.py
pybit_proxy-5.6.1.1.dist-info/LICENSE
pybit_proxy-5.6.1.1.dist-info/METADATA
pybit_proxy-5.6.1.1.dist-info/WHEEL
pybit_proxy-5.6.1.1.dist-info/top_level.txt
pybit_proxy-5.6.1.1.dist-info/RECORD
