Metadata-Version: 2.1
Name: pybit-proxy
Version: 5.6.1.1
Summary: Python3 Bybit HTTP/WebSocket API Connector
Home-page: https://github.com/Dzeravianka/pybit_proxy.git
Author: Dexter Dickinson
Author-email: dexter.dickinson@bybit.com
License: MIT License
Keywords: bybit api connector
Classifier: Development Status :: 4 - Beta
Classifier: Intended Audience :: Developers
Classifier: Topic :: Software Development :: Libraries :: Python Modules
Classifier: License :: OSI Approved :: MIT License
Classifier: Programming Language :: Python :: 3.9
Classifier: Programming Language :: Python :: 3.10
Requires-Python: >=3.6
License-File: LICENSE
Requires-Dist: requests
Requires-Dist: websocket-client
Requires-Dist: websockets
